pypesa/__init__.py
pypesa/mpesa_exceptions.py
pypesa/service_urls.py
python_pesa-0.7.dist-info/LICENSE.txt
python_pesa-0.7.dist-info/METADATA
python_pesa-0.7.dist-info/WHEEL
python_pesa-0.7.dist-info/top_level.txt
python_pesa-0.7.dist-info/RECORD
